{
  "node": {
    "4012cdbce43b2121c6cdef2f51f309e074242d3bae": {
      "workers": {
        "app/page": {
          "moduleId": 57526,
          "async": false,
          "exportedName": "getFileShares",
          "filename": "app/actions.ts"
        }
      },
      "layer": {
        "app/page": "action-browser"
      },
      "filename": "app/actions.ts",
      "exportedName": "getFileShares"
    },
    "40941e482de4f42ccb95edec6660221d0516e08788": {
      "workers": {
        "app/page": {
          "moduleId": 57526,
          "async": false,
          "exportedName": "getFiles",
          "filename": "app/actions.ts"
        }
      },
      "layer": {
        "app/page": "action-browser"
      },
      "filename": "app/actions.ts",
      "exportedName": "getFiles"
    },
    "60c024e4a58690d73c23812a08c9196438e1a69132": {
      "workers": {
        "app/page": {
          "moduleId": 57526,
          "async": false,
          "exportedName": "shareFile",
          "filename": "app/actions.ts"
        }
      },
      "layer": {
        "app/page": "action-browser"
      },
      "filename": "app/actions.ts",
      "exportedName": "shareFile"
    },
    "406e7a81ac954932304de2a55931225c66853bbb12": {
      "workers": {
        "app/page": {
          "moduleId": 57526,
          "async": false,
          "exportedName": "getSharedFiles",
          "filename": "app/actions.ts"
        }
      },
      "layer": {
        "app/page": "action-browser"
      },
      "filename": "app/actions.ts",
      "exportedName": "getSharedFiles"
    },
    "00f9a7d16ac14cda9aa8721c9d13a5b88e80f0c31c": {
      "workers": {
        "app/page": {
          "moduleId": 57526,
          "async": false,
          "exportedName": "getOutgoingShares",
          "filename": "app/actions.ts"
        }
      },
      "layer": {
        "app/page": "action-browser"
      },
      "filename": "app/actions.ts",
      "exportedName": "getOutgoingShares"
    },
    "601150663fbd8616944fcc517785e2a164d23c29d8": {
      "workers": {
        "app/page": {
          "moduleId": 57526,
          "async": false,
          "exportedName": "unshareFile",
          "filename": "app/actions.ts"
        }
      },
      "layer": {
        "app/page": "action-browser"
      },
      "filename": "app/actions.ts",
      "exportedName": "unshareFile"
    },
    "60305d12482345710e4ea80b493df9864261990fb4": {
      "workers": {
        "app/page": {
          "moduleId": 57526,
          "async": false,
          "exportedName": "changePermissions",
          "filename": "app/actions.ts"
        }
      },
      "layer": {
        "app/page": "action-browser"
      },
      "filename": "app/actions.ts",
      "exportedName": "changePermissions"
    },
    "40585f2776294156ef27ce9123ef39b5e770fdc18f": {
      "workers": {
        "app/page": {
          "moduleId": 57526,
          "async": false,
          "exportedName": "uploadFile",
          "filename": "app/actions.ts"
        }
      },
      "layer": {
        "app/page": "action-browser"
      },
      "filename": "app/actions.ts",
      "exportedName": "uploadFile"
    },
    "6034d279cf611d57eeec25a1ffed7815f0a679b768": {
      "workers": {
        "app/page": {
          "moduleId": 57526,
          "async": false,
          "exportedName": "createFolder",
          "filename": "app/actions.ts"
        }
      },
      "layer": {
        "app/page": "action-browser"
      },
      "filename": "app/actions.ts",
      "exportedName": "createFolder"
    },
    "405e156af4366a51aa1537f64461b58d8d722da2e6": {
      "workers": {
        "app/page": {
          "moduleId": 57526,
          "async": false,
          "exportedName": "deleteItem",
          "filename": "app/actions.ts"
        }
      },
      "layer": {
        "app/page": "action-browser"
      },
      "filename": "app/actions.ts",
      "exportedName": "deleteItem"
    },
    "006470ac00b67e4c5b642dae92b2f96a0825ea0bc3": {
      "workers": {
        "app/page": {
          "moduleId": 57526,
          "async": false,
          "exportedName": "getTrashFiles",
          "filename": "app/actions.ts"
        }
      },
      "layer": {
        "app/page": "action-browser"
      },
      "filename": "app/actions.ts",
      "exportedName": "getTrashFiles"
    },
    "40e18ca4e5d6ec9bf9affb87fdce6c1b1f830b4716": {
      "workers": {
        "app/page": {
          "moduleId": 57526,
          "async": false,
          "exportedName": "permanentDelete",
          "filename": "app/actions.ts"
        }
      },
      "layer": {
        "app/page": "action-browser"
      },
      "filename": "app/actions.ts",
      "exportedName": "permanentDelete"
    },
    "4014f799c6635a61d197a483e33f1edb636a04f0cd": {
      "workers": {
        "app/page": {
          "moduleId": 57526,
          "async": false,
          "exportedName": "restoreFromTrash",
          "filename": "app/actions.ts"
        }
      },
      "layer": {
        "app/page": "action-browser"
      },
      "filename": "app/actions.ts",
      "exportedName": "restoreFromTrash"
    },
    "004e041c3f96704484a7a9d46bd72cd2e8b1fea9ae": {
      "workers": {
        "app/page": {
          "moduleId": 57526,
          "async": false,
          "exportedName": "getRecentFiles",
          "filename": "app/actions.ts"
        }
      },
      "layer": {
        "app/page": "action-browser"
      },
      "filename": "app/actions.ts",
      "exportedName": "getRecentFiles"
    },
    "608051b21eb302b0869f424a9459f2a58659e71b29": {
      "workers": {
        "app/page": {
          "moduleId": 57526,
          "async": false,
          "exportedName": "renameItem",
          "filename": "app/actions.ts"
        }
      },
      "layer": {
        "app/page": "action-browser"
      },
      "filename": "app/actions.ts",
      "exportedName": "renameItem"
    },
    "6021916da99beda7f05077882d4d5c3b2a9244a101": {
      "workers": {
        "app/page": {
          "moduleId": 57526,
          "async": false,
          "exportedName": "moveItem",
          "filename": "app/actions.ts"
        }
      },
      "layer": {
        "app/page": "action-browser"
      },
      "filename": "app/actions.ts",
      "exportedName": "moveItem"
    },
    "40d56b8483b002d733c3b865bdb1f5b8e827cc804d": {
      "workers": {
        "app/page": {
          "moduleId": 57526,
          "async": false,
          "exportedName": "toggleFavorite",
          "filename": "app/actions.ts"
        }
      },
      "layer": {
        "app/page": "action-browser"
      },
      "filename": "app/actions.ts",
      "exportedName": "toggleFavorite"
    },
    "009183d60557e171b61e47d196fdc3c8fb3d51fdab": {
      "workers": {
        "app/page": {
          "moduleId": 57526,
          "async": false,
          "exportedName": "getFavorites",
          "filename": "app/actions.ts"
        }
      },
      "layer": {
        "app/page": "action-browser"
      },
      "filename": "app/actions.ts",
      "exportedName": "getFavorites"
    }
  },
  "edge": {},
  "encryptionKey": "TQg+wl6jhEQAylSr3kwzT9OW6arkFsxoKFOTya2HX8k="
}